examples/__init__.py
examples/autoencoder.py
examples/broadcasting_example.py
examples/convolutional_neural_network.py
examples/custom_loss_function.py
examples/generative_adversarial_network.py
examples/linear_regression.py
examples/logistic_regression.py
examples/matrix_factorization.py
examples/multiple_inputs_outputs.py
examples/non_scalar_output.py
examples/polynomial_regression.py
examples/recurrent_neural_network.py
examples/simple_neural_network.py
examples/using_ops.py
gradnerve-0.2.dist-info/METADATA
gradnerve-0.2.dist-info/WHEEL
gradnerve-0.2.dist-info/top_level.txt
gradnerve-0.2.dist-info/RECORD
