Metadata-Version: 2.1
Name: gradnerve
Version: 0.2
Home-page: https://github.com/yourusername/gradnerve
Author: Your Name
Author-email: your.email@example.com
License: MIT
Requires-Python: >=3.6
Requires-Dist: numpy
